torchlife/__init__.py
torchlife/_nbdev.py
torchlife/core.py
torchlife/data.py
torchlife/losses.py
torchlife/model.py
torchlife/models/__init__.py
torchlife/models/aft.py
torchlife/models/cox.py
torchlife/models/error_dist.py
torchlife/models/km.py
torchlife/models/ph.py
torchlife-0.0.2.dist-info/LICENSE
torchlife-0.0.2.dist-info/METADATA
torchlife-0.0.2.dist-info/WHEEL
torchlife-0.0.2.dist-info/entry_points.txt
torchlife-0.0.2.dist-info/top_level.txt
torchlife-0.0.2.dist-info/RECORD
